yunwu_gpt_service/__init__.py
yunwu_gpt_service/__main__.py
yunwu_gpt_service-0.1.1.dist-info/METADATA
yunwu_gpt_service-0.1.1.dist-info/WHEEL
yunwu_gpt_service-0.1.1.dist-info/entry_points.txt
yunwu_gpt_service-0.1.1.dist-info/top_level.txt
yunwu_gpt_service-0.1.1.dist-info/RECORD
