Metadata-Version: 2.4
Name: yunwu_gpt_service
Version: 0.1.1
Requires-Dist: requests>=2.0
Dynamic: requires-dist
